example_pkg/__init__.py
example_pkg/zhangyilong.py
zhangyilong-1.0.1.dist-info/METADATA
zhangyilong-1.0.1.dist-info/RECORD
zhangyilong-1.0.1.dist-info/WHEEL
zhangyilong-1.0.1.dist-info/top_level.txt
