Metadata-Version: 2.1
Name: zhangyilong
Version: 1.0.1
Summary: Text Demo
Home-page: https://github.com/pypa/sampleproject
Author: zhangyl
Author-email: 912816971@qq.com
License: UNKNOWN
Platform: UNKNOWN
Classifier: Programming Language :: Python :: 3
Classifier: License :: OSI Approved :: MIT License
Classifier: Operating System :: OS Independent
